chromakey/__init__.py
chromakey/core.py
chromakey-0.1.1.dist-info/LICENSE
chromakey-0.1.1.dist-info/METADATA
chromakey-0.1.1.dist-info/WHEEL
chromakey-0.1.1.dist-info/top_level.txt
chromakey-0.1.1.dist-info/RECORD
