Metadata-Version: 2.1
Name: chromakey
Version: 0.1.1
Home-page: https://github.com/eugeneteoh/chromakey
Author: Eugene Teoh
Author-email: eugenetwc1@gmail.com
License: MIT
License-File: LICENSE
Requires-Dist: Pillow
Requires-Dist: scipy
Requires-Dist: numpy
